{
  "name": "item",
  "version": "1.0.0",
  "data": [
    {
      "item_id": 21000,
      "item_name": "무기 이름",
      "item_type": "weapon",
      "item_effect": "아이템 효과 설명",
      "item_description": "무기 아이템은 21000부터 시작",
      "hp": 0,
      "mp": 0,
      "atk": 0,
      "def": 0,
      "magic": 0,
      "speed": 0
    },
    {
      "item_id": 21001,
      "item_name": "평범한 한손검",
      "item_type": "weapon",
      "item_effect": "atk + 5",
      "item_description": "평범한 한손검이다.",
      "hp": 0,
      "mp": 0,
      "atk": 5,
      "def": 0,
      "magic": 0,
      "speed": 0
    },
    {
      "item_id": 22000,
      "item_name": "방어구 이름",
      "item_type": "Armor",
      "item_effect": "아이템 효과 설명",
      "item_description": "방어 아이템은 22000부터 시작",
      "hp": 0,
      "mp": 0,
      "atk": 0,
      "def": 0,
      "magic": 0,
      "speed": 0
    },
    {
      "item_id": 22001,
      "item_name": "흰색 반팔",
      "item_type": "Armor",
      "item_effect": "def + 5",
      "item_description": "흰색 무지 반팔이다.",
      "hp": 0,
      "mp": 0,
      "atk": 0,
      "def": 5,
      "magic": 0,
      "speed": 0
    },
    {
      "item_id": 22002,
      "item_name": "평범한 가죽 신발",
      "item_type": "Armor",
      "item_effect": "def + 5",
      "item_description": "흰색 무지 반팔이다.",
      "hp": 0,
      "mp": 0,
      "atk": 0,
      "def": 5,
      "magic": 0,
      "speed": 0
    },
    {
      "item_id": 22003,
      "item_name": "가죽 헬멧",
      "item_type": "Armor",
      "item_effect": "def + 5",
      "item_description": "머리를 보호해주는 헬멧 형태의 머리 보호구이다.",
      "hp": 0,
      "mp": 0,
      "atk": 0,
      "def": 5,
      "magic": 0,
      "speed": 0
    },
    {
      "item_id": 22004,
      "item_name": "가죽 장갑",
      "item_type": "Armor",
      "item_effect": "def + 5",
      "item_description": "무기를 미끄러지지 않게 잡아주는 장갑이다. 작업할 때도 사용하기 좋다",
      "hp": 0,
      "mp": 0,
      "atk": 0,
      "def": 5,
      "magic": 0,
      "speed": 0
    },
    {
      "item_id": 23000,
      "item_name": "아이템 이름",
      "item_type": "Asseccory",
      "item_effect": "None",
      "item_description": "악세서리 아이템은 23000부터 시작",
      "hp": 0,
      "mp": 0,
      "atk": 0,
      "def": 5,
      "magic": 0,
      "speed": 0
    },
    {
      "item_id": 23001,
      "item_name": "흔한 목걸이",
      "item_type": "Asseccory",
      "item_effect": "speed + 0.15",
      "item_description": "상점에서 판매하는 흔한 목걸이이다.",
      "hp": 0,
      "mp": 0,
      "atk": 0,
      "def": 0,
      "magic": 0,
      "speed": 0.15
    },
    {
      "item_id": 23002,
      "item_name": "대리석 반지",
      "item_type": "Asseccory",
      "item_effect": "def + 3",
      "item_description": "누군가 재미로 만든 대리석 반지이다. 대리석으로 만들었지만 장인 정신이 느껴진다.",
      "hp": 0,
      "mp": 0,
      "atk": 0,
      "def": 3,
      "magic": 0,
      "speed": 0
    }
  ]
}
